xmljson_adv/__init__.py
xmljson_adv/__main__.py
xmljson_adv-0.1.0.dist-info/LICENSE
xmljson_adv-0.1.0.dist-info/METADATA
xmljson_adv-0.1.0.dist-info/WHEEL
xmljson_adv-0.1.0.dist-info/entry_points.txt
xmljson_adv-0.1.0.dist-info/top_level.txt
xmljson_adv-0.1.0.dist-info/RECORD
