Metadata-Version: 2.1
Name: xmljson-adv
Version: 0.1.0
Summary: Converts XML into JSON/Python dicts/arrays and vice-versa. (Modified Version)
Home-page: https://github.com/sanand0/xmljson
Author: ret2happy
Author-email: 
License: MIT
Keywords: xmljson_adv
Platform: UNKNOWN
Classifier: Development Status :: 4 - Beta
Classifier: Intended Audience :: Developers
Classifier: License :: OSI Approved :: MIT License
Classifier: Operating System :: OS Independent
Classifier: Programming Language :: Python :: 2
Classifier: Programming Language :: Python :: 2.7
Classifier: Programming Language :: Python :: 3
Classifier: Programming Language :: Python :: 3.6
Classifier: Programming Language :: Python :: 3.7
Classifier: Topic :: Software Development
Classifier: Topic :: Software Development :: Libraries :: Python Modules
License-File: LICENSE
